tex_package_ilya_goldobin/__init__.py
tex_package_ilya_goldobin/func.py
tex_py_ig-0.0.3.dist-info/LICENSE
tex_py_ig-0.0.3.dist-info/METADATA
tex_py_ig-0.0.3.dist-info/WHEEL
tex_py_ig-0.0.3.dist-info/top_level.txt
tex_py_ig-0.0.3.dist-info/RECORD
