Metadata-Version: 2.1
Name: tex-py-ig
Version: 0.0.3
Summary: Package for LaTeX generation
Author-email: Ilya Goldobin <yxtagold.iliy@gmail.com>
Project-URL: Homepage, https://github.com/pypa/sampleproject
Project-URL: Issues, https://github.com/pypa/sampleproject/issues
Classifier: Programming Language :: Python :: 3
Classifier: License :: OSI Approved :: MIT License
Classifier: Operating System :: OS Independent
Requires-Python: >=3.8
License-File: LICENSE
